foss_finder/__init__.py
foss_finder/config/__init__.py
foss_finder/config/config.py
foss_finder/config/strings.py
foss_finder/scripts/__init__.py
foss_finder/scripts/foss_finder_cli.py
foss_finder/utils/__init__.py
foss_finder/utils/csv/__init__.py
foss_finder/utils/csv/csv.py
foss_finder/utils/parsers/__init__.py
foss_finder/utils/parsers/npm_parser.py
foss_finder/utils/parsers/pypi_parser.py
foss_finder/utils/tracker/__init__.py
foss_finder/utils/tracker/project.py
foss_finder/utils/tracker/tracker.py
foss_finder/utils/user_defined_info/__init__.py
foss_finder/utils/user_defined_info/base.py
foss_finder/utils/user_defined_info/fields/__init__.py
foss_finder/utils/user_defined_info/fields/add_packages.py
foss_finder/utils/user_defined_info/fields/additional_info.py
foss_finder/utils/user_defined_info/fields/field.py
foss_finder/utils/user_defined_info/fields/multi_license_selection.py
foss_finder/utils/user_defined_info/fields/overwrites.py
foss_finder/utils/validators/__init__.py
foss_finder/utils/validators/base.py
foss_finder/utils/validators/gpl_check.py
foss_finder/utils/validators/multi_license_check.py
foss_finder-0.2.0.dist-info/DESCRIPTION.rst
foss_finder-0.2.0.dist-info/METADATA
foss_finder-0.2.0.dist-info/RECORD
foss_finder-0.2.0.dist-info/WHEEL
foss_finder-0.2.0.dist-info/entry_points.txt
foss_finder-0.2.0.dist-info/metadata.json
foss_finder-0.2.0.dist-info/top_level.txt
