Metadata-Version: 2.0
Name: foss-finder
Version: 0.2.0
Summary: Finds Open Source dependencies for a GitHub Organization and/or Project
Home-page: https://github.com/iotile/foss_finder
Author: Arch Systems Inc
Author-email: info@archsys.io
License: MIT
Keywords: FOSS,Open Source,Licenses
Platform: UNKNOWN
Classifier: Programming Language :: Python
Classifier: Programming Language :: Python :: 3
Classifier: Programming Language :: Python :: 3.6
Classifier: Development Status :: 4 - Beta
Classifier: License :: OSI Approved :: MIT License
Classifier: Operating System :: OS Independent
Classifier: Topic :: Software Development :: Libraries :: Python Modules
Requires-Dist: requirements-parser (==0.1.0)
Requires-Dist: PyGithub
